{
  "slug": "2026-06-12-crypto-research-morning-brief",
  "title": "Crypto Research Morning Brief — June 12, 2026",
  "summary": "1. OVERNIGHT MOVES",
  "body": "Morning Brief — Friday, June 12, 2026\n\n1. OVERNIGHT MOVES\n\nThe watchlist prints a third consecutive green session, extending the bounce from the June 10 low. BTC $63,691 (+1.5%), ETH $1,677.14 (+1.4%), SOL $67.12 (+2.7%). SOL leads for a second straight day — a notable reversal from the ETH-outperformance window of June 7–9. BTC dominance held flat at 56.3%, unchanged from yesterday. That is the compositional signal to track: on a green day, capital is not rotating into alts; BTC is retaining its share of the bid. No asset has reclaimed a structural level — BTC remains $11,300 below the former $75k floor, ETH is still beneath $1,700, and SOL is under $70. The CoinGecko trending board shows Plasma (XPL), Velvet (VELVET), Humanity (H), Stargate Finance (STG), Pudgy Penguins (PENGU), Audiera (BEAT), and BTC. PENGU persists from yesterday's memecoin surge, but BONK has exited the top seven. Two new low-cap entries (XPL, VELVET) and a return of STG — last seen trending on June 1 — suggest speculative scanning continues but has rotated from the BONK/PENGU corridor to new names.\n\n2. NARRATIVE PULSE\n\nThree shifts buried beneath the recovery churn:\nStargate Finance (STG) re-entering the feed. STG was absent from trending throughout the entire drawdown period (June 5–11). Its reappearance now, without a corresponding volume event, signals that the cross-chain interoperability narrative may be waking from dormancy. Traders who indexed the prediction-market and credit-market theses should note that STG — as the primary bridge/liquidity layer for cross-chain swaps — would benefit from any resurgence in DeFi activity. Durability is unconfirmed; a second consecutive day on the board would force deeper research.\nMemecoin acceleration narrowing, not broadening. PENGU remains in the top trending names for a fourth consecutive day, but BONK is absent, and no new meme tokens have entered the top seven. This is a deceleration from the pattern seen on June 8 and June 11, where two memes held simultaneous top slots. The memecoin circuit is not collapsing, but its momentum is contracting to a single name — a sign that speculative capital is tiring of high-beta churn and may soon rotate into narrative-driven infrastructure scans.\nHumanity (H) achieves multi-day durability. Humanity has now appeared in the top trending names across the June 8, 9, 10, 11, and June 12 briefs — a run matched only by HYPE's persistence during the drawdown. No vault research note exists on H, but its repeated presence during both selloffs and bounces warrants attention. Whether this is organic social consensus or coordinated positioning, it is the most durable low-cap signal on the board today.\n\nThe prediction-market and credit-market theses (Polymarket volume, DeFi lending growth) remain structurally intact but absent from the tape. They will re-rate when risk appetite returns — not during a low-volume bounce.\n\n3. THESIS CHECK\n\nThe active BTC thesis from the vault — \"wait for a reclaim of $75k on BTC with rising volume before treating this as anything other than a dead-cat bounce\" (source: 01-Market/theses/brief-2026-05-29.md) — is not challenged by today's data. BTC at $63,691 is $11,309 below that threshold. The bounce has now extended for three consecutive sessions, but volume is absent from all available data, and no structural level has been reclaimed. For traders holding long positions, the thesis remains correct: no signal to re-enter, no level to defend. The dead-cat scenario is still in play, and each green day without confirmation pushes the eventual resolution further out.\n\nThe ETH thesis remains absent from the vault, but the failure to reclaim $1,700 during a three-day risk-on bounce is a warning for any positioning expecting rotation into ETH. SOL's lead over BTC and ETH is notable but has not translated into a range breakout — $67 is still $13 below the shattered $80–82 floor.\n\n4. SIGNAL NOT TO MISS\n\nStargate Finance (STG) trending for the first time since June 1 is the single most important compositional change on today's board. Cross-chain infrastructure has been absent from narrative feeds for over a week. If STG sustains volume into Saturday, it would suggest the market is rotating back toward interoperability and DeFi connectivity — a prerequisite for any of the credit-market or prediction-market theses to re-rate.\n\n5. OPEN QUESTION\n\nIf the three-day bounce is extending on declining volume and without structural level reclaims, what catalyst — macro or protocol-specific — would be sufficient to break the dead-cat pattern, and how would traders identify it before price confirms?",
  "sourceUrl": "https://cryptocatalyst.news",
  "sourceName": "Crypto Research Autopilot",
  "category": "general",
  "tags": [
    "bitcoin",
    "defi",
    "ethereum",
    "market-analysis",
    "morning-brief",
    "narrative",
    "research",
    "solana"
  ],
  "publishedAt": "2026-06-12T10:19:36.055867+00:00",
  "imageUrl": "/images/articles/2026-06-12-crypto-research-morning-brief.png",
  "twitterThread": [],
  "standaloneTweet": "Daily crypto research brief for June 12, 2026: 1. OVERNIGHT MOVES"
}